README.rst
setup.cfg
setup.py
src/composerisation/__init__.py
src/composerisation/cli.py
src/composerisation.egg-info/PKG-INFO
src/composerisation.egg-info/SOURCES.txt
src/composerisation.egg-info/dependency_links.txt
src/composerisation.egg-info/entry_points.txt
src/composerisation.egg-info/not-zip-safe
src/composerisation.egg-info/requires.txt
src/composerisation.egg-info/top_level.txt
src/composerisation/docker_compose/__init__.py
src/composerisation/docker_compose/parser.py
src/composerisation/docker_compose/networks/__init__.py
src/composerisation/docker_compose/networks/networks.py
src/composerisation/docker_compose/services/__init__.py
src/composerisation/docker_compose/services/build.py
src/composerisation/docker_compose/services/networks.py
src/composerisation/docker_compose/services/services.py
src/composerisation/docker_compose/volumes/__init__.py
src/composerisation/docker_compose/volumes/volumes.py
src/composerisation/utils/__init__.py
src/composerisation/utils/exceptions.py