Metadata-Version: 2.1
Name: composerisation
Version: 0.1.2
Summary: A tool used to convert between Docker compose and Docker run.
Home-page: https://gitlab.com/hmajid2301/composerisation
Author: Haseeb Majid
Author-email: hello@haseebmajid.dev
License: Apache License
Keywords: Python
Platform: UNKNOWN
Classifier: Programming Language :: Python
Classifier: Intended Audience :: Developers
Classifier: Operating System :: OS Independent
Classifier: Topic :: Software Development :: Libraries :: Python Modules
Requires-Python: ~=3.6
